autosub1
