Metadata-Version: 1.0
Name: autosub1
Version: 0.4.5
Summary: Auto-generates subtitles for any video or audio file
Home-page: https://github.com/agermanidis/autosub1
Author: Anastasis Germanidis
Author-email: agermanidis@gmail.com
License: The MIT License (MIT)
